runes_cli/__init__.py
runes_cli/api.py
runes_cli/builder.py
runes_cli/cli.py
runes_cli/config.py
runes_cli/containers.py
runes_cli/file_uploader.py
runes_cli/models.py
runes_cli/persistence.py
runes_cli-0.4.5.dist-info/LICENSE
runes_cli-0.4.5.dist-info/METADATA
runes_cli-0.4.5.dist-info/WHEEL
runes_cli-0.4.5.dist-info/entry_points.txt
runes_cli-0.4.5.dist-info/top_level.txt
runes_cli-0.4.5.dist-info/RECORD
