Metadata-Version: 2.1
Name: runes-cli
Version: 0.4.5
Summary: A python CLI used to manage the Signals & Sorcery platform
Author: Steve Hiehn
Author-email: stevehiehn@gmail.com
License: GPL-3.0
Classifier: Programming Language :: Python :: 3
Classifier: License :: OSI Approved :: GNU General Public License v3 (GPLv3)
License-File: LICENSE
Requires-Dist: aiohttp
Requires-Dist: click
Requires-Dist: cryptography
Requires-Dist: docker
Requires-Dist: questionary
Requires-Dist: urllib3
Requires-Dist: requests
Requires-Dist: appdirs
